lib2opds/__init__.py
lib2opds/__main__.py
lib2opds/config.py
lib2opds/ebooks.py
lib2opds/feeds.py
lib2opds/opds.py
lib2opds/publications.py
lib2opds/repositories.py
lib2opds/sidecars.py
lib2opds/formats/__init__.py
lib2opds/formats/epub.py
lib2opds/formats/pdf.py
lib2opds/templates/acquisition-feed.html
lib2opds/templates/acquisition-feed.xml
lib2opds/templates/acquisition-feed.xsl
lib2opds/templates/base.html
lib2opds/templates/base.xsl
lib2opds/templates/navigation-feed.html
lib2opds/templates/navigation-feed.xml
lib2opds/templates/navigation-feed.xsl
lib2opds/templates/style.css
lib2opds-0.4.0.data/data/share/man/man1/lib2opds.1
lib2opds-0.4.0.data/data/share/man/man5/lib2opds-sidecar-files.5
lib2opds-0.4.0.data/data/share/man/man5/lib2opds.ini.5
lib2opds-0.4.0.dist-info/METADATA
lib2opds-0.4.0.dist-info/WHEEL
lib2opds-0.4.0.dist-info/entry_points.txt
lib2opds-0.4.0.dist-info/licenses/LICENSE
lib2opds-0.4.0.dist-info/RECORD
