Metadata-Version: 2.4
Name: lib2opds
Version: 0.4.0
Summary: Static OPDS catalog generator powered by Python
Project-URL: Homepage, https://github.com/oxdef/lib2opds
Project-URL: Documentation, https://github.com/oxdef/lib2opds/wiki
Project-URL: Repository, https://github.com/oxdef/lib2opds.git
Project-URL: Issues, https://github.com/oxdef/lib2opds/issues
Author-email: Taras Ivashchenko <oxdef@oxdef.info>
License:                     GNU GENERAL PUBLIC LICENSE
License-File: LICENSE
Keywords: ebook,epub,opds
Classifier: Development Status :: 5 - Production/Stable
Classifier: Environment :: Console
Classifier: Intended Audience :: Developers
Classifier: Intended Audience :: Information Technology
Classifier: Intended Audience :: System Administrators
Classifier: Operating System :: POSIX :: Linux
Classifier: Programming Language :: Python
Classifier: Programming Language :: Python :: 3
Classifier: Programming Language :: Python :: 3 :: Only
Classifier: Programming Language :: Python :: 3.11
Classifier: Programming Language :: Python :: 3.12
Requires-Python: >=3.11
Requires-Dist: defusedxml>=0.7.1
Requires-Dist: jinja2<4.0.0,>=3.1.2
Requires-Dist: pillow>=9.4.0
Requires-Dist: pypdf<7.0.0,>=3.4.1
